{
  "sections": {
    "07671bb2-ca21-49ba-8a12-1cc69f20dd61": {
      "type": "breadcrumbs",
      "settings": {
        "padding_top": 0,
        "padding_bottom": 0
      }
    },
    "main": {
      "type": "main-page",
      "disabled": true,
      "settings": {
        "padding_top": 0,
        "padding_bottom": 0
      }
    },
    "7710a76d-e470-486e-b3f1-46fc40184a79": {
      "type": "collapsible-content",
      "blocks": {
        "template--14871605149750__7710a76d-e470-486e-b3f1-46fc40184a79-1673988093e3aa9485-0": {
          "type": "collapsible_row",
          "settings": {
            "heading": "Do you make pickled melons or meloned pickles?",
            "icon": "question_mark",
            "row_content": "<p>Unfortunately, we do not make either at this point in time. We specialise in making things out of wood, leather, resin, etc. But who knows, one day we might try it.</p>",
            "page": ""
          }
        },
        "template--14871605149750__7710a76d-e470-486e-b3f1-46fc40184a79-1673988093e3aa9485-1": {
          "type": "collapsible_row",
          "settings": {
            "heading": "Where can you ship?",
            "icon": "question_mark",
            "row_content": "<p>For merchandise we will be able to ship almost anywhere in the world depending on the stock and where you are. </p><p>However, for the items that we make as projects, we primarily ship around New Zealand. Still, if you are from overseas and would like one of our items don't hesitate to contact us at info@melonpickle.com and let us know where you want to ship it and we will get back to you.</p>",
            "page": ""
          }
        },
        "template--14871605149750__7710a76d-e470-486e-b3f1-46fc40184a79-1673988093e3aa9485-2": {
          "type": "collapsible_row",
          "settings": {
            "heading": "How long will it take to make the items I ordered?",
            "icon": "question_mark",
            "row_content": "<p>Everything that we sell is <em>made to order</em>, so it will take slightly longer to make these items compared to mass produced items. </p><p>On the other hand, isn't it more special to know that your order is made especially for you.</p><p>After you have put in an order, you will recieve an e-mail after to give you an estimate of how long it will take to make your items. We will then send you follow-up e-mails to update you on what stage it is on whenever we can.</p>",
            "page": ""
          }
        },
        "template--14871605149750__7710a76d-e470-486e-b3f1-46fc40184a79-1673988093e3aa9485-3": {
          "type": "collapsible_row",
          "settings": {
            "heading": "How long will shipping take?",
            "icon": "question_mark",
            "row_content": "<p>In <strong>New Zealand</strong>, ideally it will take <strong>2-3 working days</strong> from the moment of us handing the shipment over to the courier.</p><p>For <strong>overseas delivery</strong>, it can take from <strong>2-3 days for neighbouring countries of NZ</strong> and <strong>up to 20 days for long distance countries</strong>.</p><p>If we become aware of any shipping delays we will let you know as soon as possible if it will impact your items. </p>",
            "page": ""
          }
        },
        "d45b820e-613b-42ee-91ca-a3d182c182c3": {
          "type": "collapsible_row",
          "settings": {
            "heading": "Do you offer free delivery?",
            "icon": "question_mark",
            "row_content": "<p>Unfortunately, we cannot offer free delivery.</p><p>However, depending on the item ordered, we can possibly personally deliver or organise a pick-up if you are in Wellington.</p>",
            "page": ""
          }
        },
        "1c752980-13b7-49bb-81cc-c0fab82beb8a": {
          "type": "collapsible_row",
          "settings": {
            "heading": "Can I change my order?",
            "icon": "question_mark",
            "row_content": "<p>For Merchandise, you can change an order that has already been submitted <strong>unless it has the status of '</strong><em><strong>Being Fulfilled</strong></em>' (or any stage after that), Click the <em>Change order</em> button from your order view and edit the products and shipping options from there.</p><p>Note, that changing a product within an order (e.g. altering a product's variant, size, design file, or mockup) that has the '<em>Waiting for Fulfillment</em>' status, or setting its status to <em>On Hold</em>, will reset the order deadline. This may result in a longer fulfillment time. However, changing a shipping address or rate <strong>will not</strong> reset the order deadline.</p><p>For all other items, we will be able to change it as long as the request is made within 24 hours of the order being submitted. Please contact us if it falls outside of the 24 hours and we will see what we can do. </p>",
            "page": ""
          }
        },
        "4aea03af-b775-400e-8edf-7fdbaefb3d6d": {
          "type": "collapsible_row",
          "settings": {
            "heading": "Which companies do you use to deliver your items?",
            "icon": "question_mark",
            "row_content": "<p>We normally use NZ Post or DHL. </p><p>We use NZ Post to ship items around New Zealand and for internatinal items we use DHL.</p><p>However, if there are unforseen circumstances and we need to use a different delivery service we will let you know.</p>",
            "page": ""
          }
        },
        "6119b01b-208b-4a8f-a5a8-e138004a0035": {
          "type": "collapsible_row",
          "settings": {
            "heading": "What are your standard practices to be eco-friendly?",
            "icon": "question_mark",
            "row_content": "<p>Sustainability is important to us. We try our best to be greener every step of the way. This is done through the following ways:</p><ul><li><strong>All our items are made to order </strong>- From merchandise to our leather wallets. We only make your items once you have confirmed your order. This would mean no over production, we reduce our uneccessary wastes and we reduce excess unwanted stock.</li><li><strong>We use recycled and organic materials for our merchandise</strong> - Most of our merchandise are either recycled, can be recycled or are biodegradeable. </li><li><strong>We use recycle materials for our projects </strong>- From recycled wood from old buldosed structures to leather offcuts. We try to find the hidden gems everywhere and try make it into something fun. </li><li><strong>We look for ecofriendly and sustainable supplies/suppliers - </strong>There are some items that can't be found in the recyclers. So with each project we look for material that is balanced. Eco friendly and meets the purpose for the project.</li></ul><p>As we know more we will do more. </p>",
            "page": ""
          }
        },
        "7a8eaeed-0bd6-4d17-95ed-2c43129102f8": {
          "type": "collapsible_row",
          "settings": {
            "heading": "What is taking my order so long?",
            "icon": "question_mark",
            "row_content": "<p>All items are made to order. Please take note that this means that after you have submitted your order we will purchase materials and make everything individually. We have a 3d printer and laser cutter but other than that everything is made by hand. </p><p>We appreciate your patience.</p>",
            "page": ""
          }
        },
        "2a58a9bb-e25f-46fd-80e8-a48f0fd9c695": {
          "type": "collapsible_row",
          "settings": {
            "heading": "What are your eco-friendly materials for your projects?",
            "icon": "question_mark",
            "row_content": "<p>We use the following:</p><ul><li><strong>Recycled timber</strong> from recycle centres and private sellers. These items are normally procured from old structures that have been knocked down.</li><li><strong>Leather scraps </strong>from fabric stores. These are normally best for small projects.</li><li><strong>MDF </strong>is made up of mainly wood fibers, wood shavings and portions of wood that might normally be thrown away.</li><li><strong>Bamboo Ply </strong>is made up of bamboo plants. They have a rapid growth rate and are quite easy to grow as it pretty much looks after itself.</li></ul>",
            "page": ""
          }
        },
        "f540cd1a-b0d8-4684-8217-4de3e1805200": {
          "type": "collapsible_row",
          "settings": {
            "heading": "What is your return policy?",
            "icon": "question_mark",
            "row_content": "<p>We are happy to have a discussion if an item can be repaired, refunded or replaced if the items is faulty.</p><p>However, we cannot grant any returns if you have changed your mind with your purchase.</p>",
            "page": ""
          }
        },
        "3f71eb2f-24a9-4ba3-979d-15b41a36bc62": {
          "type": "collapsible_row",
          "settings": {
            "heading": "Do you have a physical store?",
            "icon": "question_mark",
            "row_content": "<p>We apologise for the inconvenience but we do not currently have a physical store.</p>",
            "page": ""
          }
        },
        "319bb352-86c1-46d6-b4d0-4dbc04847ab5": {
          "type": "collapsible_row",
          "settings": {
            "heading": "When is your next video coming out?",
            "icon": "question_mark",
            "row_content": "<p>We will try to post videos as much as we can. At this point and time, we aim to post two videos on Youtube per month but that really depends on how busy we are. </p><p>We will probably post more shorts and photos on <a href=\"https://www.instagram.com/melonpicklenz/\" target=\"_blank\" title=\"https://www.instagram.com/melonpicklenz/\">Instragram</a>, <a href=\"https://www.facebook.com/MelonPickle\" target=\"_blank\" title=\"https://www.facebook.com/MelonPickle\">Facebook,</a> <a href=\"https://www.tiktok.com/@melonpicklenz\" target=\"_blank\" title=\"https://www.tiktok.com/@melonpicklenz\">TikTok </a>and <a href=\"https://www.youtube.com/@melonpickle\" target=\"_blank\" title=\"https://www.youtube.com/@melonpickle\">Youtube</a>.</p>",
            "page": ""
          }
        },
        "be85b9b3-c054-45e6-9c8e-61e40f02901b": {
          "type": "collapsible_row",
          "settings": {
            "heading": "Where did the name 'MelonPickle' come from?",
            "icon": "question_mark",
            "row_content": "<p>During the first month of our relationship, Nicole had to go to the Philippines to visit family. Philippines has such delicious fruits and so she would have a lot of watermelon and rockmelon as they were very refreshing. Which helped a lot cause it was extremetly hot over there. And so Anthony started calling her 'melon'. However, Nicole didn't like that nickname so to tease him, she started calling Anthony 'Pickle'. She thought that he would hate that nickname but no. He liked it. And so as time passed the nicknames sounded more cute and endearing. That is where MelonPickle came from.</p>",
            "page": ""
          }
        },
        "43fd2acf-1c7d-4564-810d-4ce4793ad553": {
          "type": "collapsible_row",
          "settings": {
            "heading": "Why do you do this?",
            "icon": "question_mark",
            "row_content": "<p>We love making things. It brings us so much joy. </p><p>It takes a lot of time and energy but seeing the end result makes it all worth it. And to be able to share it with you is fantastic.</p>",
            "page": ""
          }
        },
        "8718471e-20e2-473b-89af-44cb4b436698": {
          "type": "collapsible_row",
          "settings": {
            "heading": "Is this your full-time job?",
            "icon": "question_mark",
            "row_content": "<p>Nope. Anthony is a Web Developer and Nicole is a Quantity Surveyor. </p>",
            "page": ""
          }
        },
        "b8d168ef-5722-4648-af13-57e7f307b59d": {
          "type": "collapsible_row",
          "settings": {
            "heading": "Where are you from?",
            "icon": "question_mark",
            "row_content": "<p>We live in Wellington, New Zealand.</p>",
            "page": ""
          }
        },
        "d120e83b-a7f0-43ad-9685-89543972784f": {
          "type": "collapsible_row",
          "settings": {
            "heading": "What does 'perfectly imperfect' mean?",
            "icon": "question_mark",
            "row_content": "<p>This means accepted and loved warts and all. </p><p>This is how we describe the things that we create. It might not be flawless or the most polished quality but it is usefull, beautiful and it is excellent. We are not machines. We incorporate a unique 'fingerprint' in everything we make. </p>",
            "page": ""
          }
        }
      },
      "block_order": [
        "template--14871605149750__7710a76d-e470-486e-b3f1-46fc40184a79-1673988093e3aa9485-0",
        "template--14871605149750__7710a76d-e470-486e-b3f1-46fc40184a79-1673988093e3aa9485-1",
        "template--14871605149750__7710a76d-e470-486e-b3f1-46fc40184a79-1673988093e3aa9485-2",
        "template--14871605149750__7710a76d-e470-486e-b3f1-46fc40184a79-1673988093e3aa9485-3",
        "d45b820e-613b-42ee-91ca-a3d182c182c3",
        "1c752980-13b7-49bb-81cc-c0fab82beb8a",
        "4aea03af-b775-400e-8edf-7fdbaefb3d6d",
        "6119b01b-208b-4a8f-a5a8-e138004a0035",
        "7a8eaeed-0bd6-4d17-95ed-2c43129102f8",
        "2a58a9bb-e25f-46fd-80e8-a48f0fd9c695",
        "f540cd1a-b0d8-4684-8217-4de3e1805200",
        "3f71eb2f-24a9-4ba3-979d-15b41a36bc62",
        "319bb352-86c1-46d6-b4d0-4dbc04847ab5",
        "be85b9b3-c054-45e6-9c8e-61e40f02901b",
        "43fd2acf-1c7d-4564-810d-4ce4793ad553",
        "8718471e-20e2-473b-89af-44cb4b436698",
        "b8d168ef-5722-4648-af13-57e7f307b59d",
        "d120e83b-a7f0-43ad-9685-89543972784f"
      ],
      "settings": {
        "caption": "",
        "heading": "Frequently Asked Questions",
        "heading_size": "h1",
        "heading_alignment": "center",
        "layout": "row",
        "color_scheme": "background-1",
        "container_color_scheme": "background-2",
        "open_first_collapsible_row": false,
        "image_ratio": "adapt",
        "desktop_layout": "image_second",
        "padding_top": 0,
        "padding_bottom": 36
      }
    },
    "newsletter": {
      "type": "newsletter",
      "blocks": {
        "heading": {
          "type": "heading",
          "settings": {
            "heading": "SUBSCRIBE TO OUR EMAILS",
            "heading_size": "h1"
          }
        },
        "paragraph": {
          "type": "paragraph",
          "settings": {
            "text": "<p>Be the first to know about new collections and exclusive offers.</p>"
          }
        },
        "email-form": {
          "type": "email_form",
          "settings": {
          }
        }
      },
      "block_order": [
        "heading",
        "paragraph",
        "email-form"
      ],
      "settings": {
        "color_scheme": "accent-1",
        "full_width": true,
        "padding_top": 40,
        "padding_bottom": 40
      }
    }
  },
  "order": [
    "07671bb2-ca21-49ba-8a12-1cc69f20dd61",
    "main",
    "7710a76d-e470-486e-b3f1-46fc40184a79",
    "newsletter"
  ]
}
